llama_index/embeddings/openai_like/__init__.py
llama_index/embeddings/openai_like/base.py
llama_index_embeddings_openai_like-0.2.2.dist-info/METADATA
llama_index_embeddings_openai_like-0.2.2.dist-info/WHEEL
llama_index_embeddings_openai_like-0.2.2.dist-info/licenses/LICENSE
llama_index_embeddings_openai_like-0.2.2.dist-info/RECORD
