Metadata-Version: 2.4
Name: llama-index-embeddings-openai-like
Version: 0.2.2
Summary: llama-index embeddings openai integration
Author-email: Your Name <you@example.com>
License-Expression: MIT
License-File: LICENSE
Requires-Python: <4.0,>=3.9
Requires-Dist: llama-index-embeddings-openai<0.6,>=0.5.0
